testproject1234
