Metadata-Version: 2.1
Name: testproject1234
Version: 1.0
Summary: Test Project
Home-page: https://github.com/hhslepicka/testproject1234
Author: hhslepicka
License: BSD
Platform: UNKNOWN
